igeBullet.cpython-39-darwin.so
igeBullet-0.5.1.dist-info/LICENSE
igeBullet-0.5.1.dist-info/METADATA
igeBullet-0.5.1.dist-info/WHEEL
igeBullet-0.5.1.dist-info/top_level.txt
igeBullet-0.5.1.dist-info/RECORD
